file_catalog/__init__.py
file_catalog/__main__.py
file_catalog/argbuilder.py
file_catalog/config.py
file_catalog/deconfliction.py
file_catalog/mongo.py
file_catalog/py.typed
file_catalog/server.py
file_catalog/urlargparse.py
file_catalog/utils.py
file_catalog/data/www/base.css
file_catalog/data/www_templates/account.html
file_catalog/data/www_templates/base.html
file_catalog/data/www_templates/index.html
file_catalog/data/www_templates/login.html
file_catalog/schema/__init__.py
file_catalog/schema/types.py
file_catalog/schema/validation.py
wipac_file_catalog-1.9.12.dist-info/LICENSE
wipac_file_catalog-1.9.12.dist-info/METADATA
wipac_file_catalog-1.9.12.dist-info/WHEEL
wipac_file_catalog-1.9.12.dist-info/top_level.txt
wipac_file_catalog-1.9.12.dist-info/RECORD
