Metadata-Version: 2.1
Name: wipac-file-catalog
Version: 1.9.12
Summary: Store file metadata information in a file catalog
Home-page: https://github.com/WIPACrepo/file_catalog
Download-URL: https://pypi.org/project/wipac-file-catalog/
Author: WIPAC Developers
Author-email: developers@icecube.wisc.edu
License: MIT
Project-URL: Tracker, https://github.com/WIPACrepo/file_catalog/issues
Project-URL: Source, https://github.com/WIPACrepo/file_catalog
Keywords: metadata,data,warehouse,archive,L2,PFDST,PFFilt,PFRaw,i3,simulation,iceprod,WIPAC,IceCube
Classifier: Development Status :: 5 - Production/Stable
Classifier: License :: OSI Approved :: MIT License
Classifier: Programming Language :: Python :: 3.10
Classifier: Programming Language :: Python :: 3.11
Classifier: Programming Language :: Python :: 3.12
Requires-Python: <3.13,>=3.10
License-File: LICENSE
Requires-Dist: coloredlogs
Requires-Dist: ldap3
Requires-Dist: motor <3
Requires-Dist: pymongo <4
Requires-Dist: requests
Requires-Dist: requests-futures
Requires-Dist: requests-toolbelt
Requires-Dist: tornado
Requires-Dist: wipac-rest-tools[telemetry]
Provides-Extra: dev
Requires-Dist: crawler ; extra == 'dev'
Requires-Dist: flake8 ; extra == 'dev'
Requires-Dist: more-itertools ; extra == 'dev'
Requires-Dist: mypy ; extra == 'dev'
Requires-Dist: pytest ; extra == 'dev'
Requires-Dist: pytest-asyncio ; extra == 'dev'
Requires-Dist: pytest-cov ; extra == 'dev'
Requires-Dist: ruff ; extra == 'dev'
Requires-Dist: types-PyMySQL ; extra == 'dev'
Requires-Dist: types-python-dateutil ; extra == 'dev'
Requires-Dist: types-requests ; extra == 'dev'
Provides-Extra: mypy
Requires-Dist: crawler ; extra == 'mypy'
Requires-Dist: flake8 ; extra == 'mypy'
Requires-Dist: more-itertools ; extra == 'mypy'
Requires-Dist: mypy ; extra == 'mypy'
Requires-Dist: pytest ; extra == 'mypy'
Requires-Dist: pytest-asyncio ; extra == 'mypy'
Requires-Dist: pytest-cov ; extra == 'mypy'
Requires-Dist: ruff ; extra == 'mypy'
Requires-Dist: types-PyMySQL ; extra == 'mypy'
Requires-Dist: types-python-dateutil ; extra == 'mypy'
Requires-Dist: types-requests ; extra == 'mypy'
